kahanit/__init__.py
kahanit-0.0.0.dist-info/METADATA
kahanit-0.0.0.dist-info/RECORD
kahanit-0.0.0.dist-info/WHEEL
kahanit-0.0.0.dist-info/top_level.txt
