Metadata-Version: 2.1
Name: kahanit
Version: 0.0.0
Summary: Kahanit
Home-page: https://www.kahanit.com/
Author: Kahanit
Author-email: care@kahanit.com
License: UNKNOWN
Platform: UNKNOWN
Classifier: Programming Language :: Python :: 3
Classifier: License :: OSI Approved :: MIT License
Classifier: Operating System :: OS Independent
